graiax/msgparse/__init__.py
graiax_msgparse-0.0.4.dist-info/LICENSE
graiax_msgparse-0.0.4.dist-info/WHEEL
graiax_msgparse-0.0.4.dist-info/METADATA
graiax_msgparse-0.0.4.dist-info/RECORD
