Metadata-Version: 2.1
Name: graiax-msgparse
Version: 0.0.4
Summary: A argparse for MessageChain in Graia Framework
Home-page: https://github.com/I-love-study/graiax-msgparse
License: AGPL-3.0
Author: I_love_study
Author-email: 1450069615@qq.com
Requires-Python: >=3.8,<4.0
Classifier: License :: OSI Approved :: GNU Affero General Public License v3
Classifier: Programming Language :: Python :: 3
Classifier: Programming Language :: Python :: 3.8
Classifier: Programming Language :: Python :: 3.9
Project-URL: Repository, https://github.com/I-love-study/graiax-msgparse
